smartdash/__init__.py
smartdash/__main__.py
smartdash/dash.py
smartdash/smartdash_server.py
smartdash-0.0.1.dev22.dist-info/METADATA
smartdash-0.0.1.dev22.dist-info/WHEEL
smartdash-0.0.1.dev22.dist-info/entry_points.txt
smartdash-0.0.1.dev22.dist-info/top_level.txt
smartdash-0.0.1.dev22.dist-info/RECORD
