Metadata-Version: 2.1
Name: smartdash
Version: 0.0.1.dev22
Summary: python logging client for SmartDash
Home-page: https://github.com/notAI-tech/smartdash
Author: BEDAPUDI PRANEETH
Author-email: praneeth@bpraneeth.com
License: MIT
Classifier: License :: OSI Approved :: MIT License
Classifier: Programming Language :: Python
Classifier: Programming Language :: Python :: 3
Classifier: Programming Language :: Python :: 3.6
Classifier: Programming Language :: Python :: Implementation :: CPython
Requires-Python: >=3.6.0
Requires-Dist: requests
Requires-Dist: liteindex
Requires-Dist: streamlit
Requires-Dist: plotly
Requires-Dist: gevent
Requires-Dist: falcon
Requires-Dist: gunicorn
